[
	{
		"category": "POSITION",
		"keywords": [
			"position",
			"inset",
			"top",
			"right",
			"bottom",
			"left",
			"z-index"
		]
	},
	{
		"category": "LAYOUT",
		"keywords": [
			"display",
			"visibility",
			"overflow...",
			"flex...",
			"justify-content",
			"align-items",
			"align-content",
			"place-content",
			"align-self",
			"order",
			"gap",
			"row-gap",
			"column-gap",
			"grid..."
		]
	},
	{
		"category": "BOX",
		"keywords": [
			"width",
			"min-width",
			"max-width",
			"height",
			"min-height",
			"max-height",
			"aspect-ratio",
			"margin...",
			"padding...",
			"border..."
		]
	},
	{
		"category": "COLOR",
		"keywords": [
			"color",
			"background...",
			"opacity",
			"box-shadow"
		]
	},
	{
		"category": "TYPO",
		"keywords": [
			"font",
			"font-family",
			"font-size",
			"font-weight",
			"font-style",
			"font...",
			"font-stretch",
			"line-height",
			"letter-spacing",
			"word-spacing",
			"text-align",
			"text-transform",
			"text-decoration....",
			"text-underline-offset",
			"white-space"
		]
	},
	{
		"category": "ANIMATION",
		"keywords": [
			"transform...",
			"transition...",
			"animation..."
		]
	}
]